robber/__init__.py
robber/bad_expectation.py
robber/constants.py
robber/custom_explanation.py
robber/expect.py
robber/explanation.py
robber/matchers/__init__.py
robber/matchers/base.py
robber/matchers/boolean.py
robber/matchers/callable.py
robber/matchers/called.py
robber/matchers/called_once.py
robber/matchers/called_once_with.py
robber/matchers/called_with.py
robber/matchers/contain.py
robber/matchers/equal.py
robber/matchers/ever_called_with.py
robber/matchers/exception.py
robber/matchers/identical.py
robber/matchers/instanceof.py
robber/matchers/length.py
robber/matchers/mock_mixin.py
robber/matchers/numbers.py
robber/matchers/regexp.py
robber/matchers/respond_to.py
robber/matchers/truthy.py
robber/matchers/types.py
robber-1.1.5.dist-info/LICENSE
robber-1.1.5.dist-info/METADATA
robber-1.1.5.dist-info/WHEEL
robber-1.1.5.dist-info/top_level.txt
robber-1.1.5.dist-info/RECORD
