Metadata-Version: 2.1
Name: robber
Version: 1.1.5
Summary: BDD / TDD assertion library for Python
Home-page: https://github.com/vesln/robber.py
Author: Tao Liang
Author-email: tao@synapse-ai.com
License: UNKNOWN
Platform: UNKNOWN
Classifier: Programming Language :: Python
Classifier: Programming Language :: Python :: 3
Classifier: Development Status :: 5 - Production/Stable
Classifier: Intended Audience :: Developers
Classifier: License :: OSI Approved :: MIT License
Classifier: Operating System :: OS Independent
Classifier: Topic :: Software Development :: Libraries :: Python Modules
Classifier: Topic :: Software Development :: Testing
Requires-Dist: mock
Requires-Dist: termcolor
